autoscale_aws/__init__.py
autoscale_aws/batch_daemon_autoscale_cli.py
autoscale_aws/batch_daemon_launch_cli.py
autoscale_aws/batch_daemon_monitor_cli.py
autoscale_aws/util_aws.py
autoscale_aws/util_batch.py
autoscale_aws/util_cpu.py
autoscale_aws/util_log.py
autoscaleaws-12.0.2.dist-info/METADATA
autoscaleaws-12.0.2.dist-info/RECORD
autoscaleaws-12.0.2.dist-info/WHEEL
autoscaleaws-12.0.2.dist-info/entry_points.txt
autoscaleaws-12.0.2.dist-info/top_level.txt
batch_backup/__init__.py
batch_backup/batch_daemon_autoscale_cli.py
batch_backup/batch_daemon_launch_cli.py
batch_backup/batch_daemon_monitor_cli.py
batch_backup/util_batch.py
batch_backup/util_cpu.py
